{
    "sectionTitle": "My Skills",
    "categories": [
        {
            "icon": "settings",
            "title": "Systems Implementation & Support",
            "items": ["Systems Analysis", "Implementation & Testing", "Troubleshooting", "QA Support", "Documentation", "Process Improvement"]
        },
        {
            "icon": "pie-chart",
            "title": "Data Analysis & Reporting",
            "items": ["Excel", "Power BI", "Google Sheets", "SQL / MySQL", "Data Validation", "Reporting Dashboards"]
        },
        {
            "icon": "code",
            "title": "Automation & Collaboration",
            "items": ["Python", "PHP", "ETL Automation", "Workflow Automation", "Git / GitHub", "End-User Training", "Stakeholder Communication"]
        },
        {
            "icon": "monitor",
            "title": "Operating Systems",
            "items": ["Windows", "Linux", "Security Baselines", "Updates & Patching"]
        },
        {
            "icon": "server",
            "title": "Infrastructure & Virtualization",
            "items": ["Windows Server", "Active Directory", "VirtualBox", "VMware", "Lab Deployment"]
        },
        {
            "icon": "share-2",
            "title": "Networking Fundamentals",
            "items": ["TCP/IP", "DNS/DHCP", "VLAN Basics", "VPN Basics"]
        },
        {
            "icon": "globe",
            "title": "Web & Deployment",
            "items": ["HTML / CSS / JS", "Tailwind CSS", "Netlify", "Vercel", "Decap CMS", "CI/CD Pipelines"]
        }
    ]
}
